MANIFEST.in
README.rst
setup.py
tests/__init__.py
unittest_xml.egg-info/PKG-INFO
unittest_xml.egg-info/SOURCES.txt
unittest_xml.egg-info/dependency_links.txt
unittest_xml.egg-info/top_level.txt
xmltest/__init__.py
xmltest/mixin.py