Metadata-Version: 1.0
Name: unittest-xml
Version: 0.2.2
Summary: Additional assertion methods for testing XML
Home-page: https://github.com/codeinthehole/unittest-xml
Author: David Winterbottom
Author-email: david.winterbottom@tangentlabs.co.uk
License: UNKNOWN
Keywords: XML,testing
Platform: linux
